ss_quick/__init__.py
ss_quick/command_line.py
ss_quick/gui_config_loader.py
ss_quick/latency_tester.py
ss_quick/logger.py
ss_quick/main_cli.py
ss_quick-0.0.2.dist-info/METADATA
ss_quick-0.0.2.dist-info/WHEEL
ss_quick-0.0.2.dist-info/entry_points.txt
ss_quick-0.0.2.dist-info/top_level.txt
ss_quick-0.0.2.dist-info/RECORD
