Metadata-Version: 2.1
Name: ss-quick
Version: 0.0.2
Summary: A tool loading gui-config.json for ss-local
Home-page: https://github.com/Campanula/ss-quick
Author: ChaneyZorn
Author-email: chaneyzorn@gmail.com
License: MIT
Platform: UNKNOWN
Classifier: Environment :: Console
Classifier: License :: OSI Approved :: MIT License
Classifier: Programming Language :: Python :: 3.6
Classifier: Operating System :: POSIX :: Linux
Classifier: Topic :: Internet :: Proxy Servers
Requires-Python: >=3.6
